MANIFEST.in
README.rst
setup.py
docs/HISTORY.txt
docs/LICENSE.GPL
docs/LICENSE.txt
docs/screenshot1.png
docs/screenshot2.png
ftw/__init__.py
ftw.tabbedview.egg-info/PKG-INFO
ftw.tabbedview.egg-info/SOURCES.txt
ftw.tabbedview.egg-info/dependency_links.txt
ftw.tabbedview.egg-info/entry_points.txt
ftw.tabbedview.egg-info/namespace_packages.txt
ftw.tabbedview.egg-info/not-zip-safe
ftw.tabbedview.egg-info/requires.txt
ftw.tabbedview.egg-info/top_level.txt
ftw/tabbedview/__init__.py
ftw/tabbedview/caching.py
ftw/tabbedview/config.py
ftw/tabbedview/configure.zcml
ftw/tabbedview/defaulttab.py
ftw/tabbedview/dependencies.zcml
ftw/tabbedview/interfaces.py
ftw/tabbedview/setuphandlers.py
ftw/tabbedview/statestorage.py
ftw/tabbedview/testing.py
ftw/tabbedview/browser/__init__.py
ftw/tabbedview/browser/batching.pt
ftw/tabbedview/browser/config.py
ftw/tabbedview/browser/configure.zcml
ftw/tabbedview/browser/fallback.pt
ftw/tabbedview/browser/fallback.py
ftw/tabbedview/browser/generic.pt
ftw/tabbedview/browser/listing.py
ftw/tabbedview/browser/menu.pt
ftw/tabbedview/browser/searchbox.pt
ftw/tabbedview/browser/searchbox.py
ftw/tabbedview/browser/select_all.pt
ftw/tabbedview/browser/selection.pt
ftw/tabbedview/browser/tabbed.pt
ftw/tabbedview/browser/tabbed.py
ftw/tabbedview/browser/tabbedview.scss
ftw/tabbedview/browser/resources/ftwtable.js
ftw/tabbedview/browser/resources/spinner.gif
ftw/tabbedview/browser/resources/tabbedview.css
ftw/tabbedview/browser/resources/tabbedview.js
ftw/tabbedview/browser/resources/tabbedview_menu.png
ftw/tabbedview/browser/resources/upload.js
ftw/tabbedview/locales/ftw.tabbedview-manual.pot
ftw/tabbedview/locales/ftw.tabbedview.pot
ftw/tabbedview/locales/de/LC_MESSAGES/ftw.tabbedview.po
ftw/tabbedview/locales/en/LC_MESSAGES/ftw.tabbedview.po
ftw/tabbedview/locales/fr/LC_MESSAGES/ftw.tabbedview.po
ftw/tabbedview/profiles/default/cssregistry.xml
ftw/tabbedview/profiles/default/ftw.tabbedview_default.txt
ftw/tabbedview/profiles/default/jsregistry.xml
ftw/tabbedview/profiles/default/metadata.xml
ftw/tabbedview/profiles/default/registry.xml
ftw/tabbedview/profiles/default/viewlets.xml
ftw/tabbedview/profiles/extjs/actions.xml
ftw/tabbedview/profiles/extjs/ftw.tabbedview_extjs.txt
ftw/tabbedview/profiles/extjs/jsregistry.xml
