Metadata-Version: 2.1
Name: ftw.tabbedview
Version: 4.2.1
Summary: A generic tabbed view for plone content types.
Home-page: https://github.com/4teamwork/ftw.tabbedview
Author: 4teamwork AG
Author-email: mailto:info@4teamwork.ch
Maintainer: Jonas Baumann
License: GPL2
Keywords: ftw tabbedview table listing
Platform: UNKNOWN
Classifier: Framework :: Plone
Classifier: Framework :: Plone :: 4.3
Classifier: Framework :: Plone :: 5.1
Classifier: Programming Language :: Python
Classifier: Topic :: Software Development :: Libraries :: Python Modules
Provides-Extra: plone4.3
Provides-Extra: tests
Provides-Extra: extjs
Provides-Extra: quickupload
